{
  "name": "<%= name %>",
  "version": "0.0.1",
  "main": [
    "<%= name %>.html"
  ],
  "ignore": [
    ".*",
    "npm-debug.log",
    "gulpfile.js",
    "sass",
    "bower_components",
    "node_modules",
    "test",
    "OSS_Notice.pdf",
    "scripts",
    ".github",
    "<%=name %>.png",
    "LICENSE.md",
    "CONTRIBUTING.md",
    "HISTORY.md"
  ],
  "dependencies": {
    "polymer": "^1.6.0",
    "px-theme": "~1.1.2"
  },
  "devDependencies": {
    "px-forms-design": "#~0.3.15",
    "px-tables-design": "#~0.3.12",
    "iron-demo-helpers": "PolymerElements/iron-demo-helpers#^1.2.3",
    "px-polymer-font-awesome":"^0.1.8",
    "px-tabs": "~0.4.0",
    "px-api-viewer": "^0.1.0",
    "px-demo-snippet": "^0.4.0",
    "px-list-inline-design": "^0.2.11",
    "px-toggle-design": "^0.2.12",
    "px-headings-design": "^0.2.14",
    "px-actionable-text-icons-design": "^0.0.3",
    "px-code-design": "^0.2.11",
    "px-list-bare-design": "^0.2.13",
    "px-meta-lists-design": "^0.3.4",
    "px-dropdown": "^0.11.2",
    <%- devDependencies.join('\n        ') %>
    "px-starter-kit-design": "~0.6.0"
  }
}
